django_bulmacss/__init__.py
django_bulmacss/admin.py
django_bulmacss/apps.py
django_bulmacss/models.py
django_bulmacss/tests.py
django_bulmacss/views.py
django_bulmacss/migrations/__init__.py
django_bulmacss/static/bulma/bulma.min.css
django_bulmacss/static/bulma/feather.min.js
django_bulmacss/static/bulma/feather.min.js.map
django_bulmacss/static/bulma/jdenticon.min.js
django_bulmacss/static/bulma/jdenticon.min.js.map
django_bulmacss/static/bulma/login_bg.jpg
django_bulmacss/templates/attrs.html
django_bulmacss/templates/avatar.html
django_bulmacss/templates/base.html
django_bulmacss/templates/breadcrumb.html
django_bulmacss/templates/console.html
django_bulmacss/templates/dir_tree.html
django_bulmacss/templates/empty.html
django_bulmacss/templates/field_display.html
django_bulmacss/templates/field_horizontal.html
django_bulmacss/templates/file_line.html
django_bulmacss/templates/filters.html
django_bulmacss/templates/footer.html
django_bulmacss/templates/form_display.html
django_bulmacss/templates/form_horizontal.html
django_bulmacss/templates/form_modal.html
django_bulmacss/templates/form_submit.html
django_bulmacss/templates/formset_widget_display.html
django_bulmacss/templates/index.html
django_bulmacss/templates/main_menu.html
django_bulmacss/templates/menus.html
django_bulmacss/templates/messages.html
django_bulmacss/templates/modal.html
django_bulmacss/templates/navbar.html
django_bulmacss/templates/pagination.html
django_bulmacss/templates/profile_menu.html
django_bulmacss/templates/render_boolean.html
django_bulmacss/templates/search_bar.html
django_bulmacss/templates/sorting.html
django_bulmacss/templates/account/account_inactive.html
django_bulmacss/templates/account/base.html
django_bulmacss/templates/account/email.html
django_bulmacss/templates/account/email_confirm.html
django_bulmacss/templates/account/index.html
django_bulmacss/templates/account/login.html
django_bulmacss/templates/account/logout.html
django_bulmacss-0.0.4.dist-info/METADATA
django_bulmacss-0.0.4.dist-info/WHEEL
django_bulmacss-0.0.4.dist-info/licenses/LICENSE
django_bulmacss-0.0.4.dist-info/RECORD
