Metadata-Version: 2.1
Name: django_bulmacss
Version: 0.0.4
Summary: django-bulmacss 是一个基于 Bulma CSS 的常用 HTML 模板库，为 Django 开发者提供了快速搭建 Django 应用程序的解决方案。
Project-URL: Homepage, https://github.com/ChanMo/django-bulma
Project-URL: Issues, https://github.com/ChanMo/django-bulma/issues
Author-email: ChanMo <chan.mo@outlook.com>
License-File: LICENSE
Keywords: bulma,django,django-bulma,django-bulmacss
Classifier: License :: OSI Approved :: MIT License
Classifier: Operating System :: OS Independent
Classifier: Programming Language :: Python :: 3
Requires-Python: >=3.8
